colcon_installed_package_information/__init__.py
colcon_installed_package_information/__main__.py
colcon_installed_package_information/package_augmentation/__init__.py
colcon_installed_package_information/package_augmentation/colcon_index.py
colcon_installed_package_information/package_augmentation/python.py
colcon_installed_package_information/package_discovery/__init__.py
colcon_installed_package_information/package_discovery/prefix_path.py
colcon_installed_package_information/package_identification/__init__.py
colcon_installed_package_information-0.2.1.dist-info/LICENSE
colcon_installed_package_information-0.2.1.dist-info/METADATA
colcon_installed_package_information-0.2.1.dist-info/WHEEL
colcon_installed_package_information-0.2.1.dist-info/entry_points.txt
colcon_installed_package_information-0.2.1.dist-info/top_level.txt
colcon_installed_package_information-0.2.1.dist-info/zip-safe
colcon_installed_package_information-0.2.1.dist-info/RECORD
