Metadata-Version: 2.1
Name: colcon-installed-package-information
Version: 0.2.1
Summary: Extensions for colcon to inspect packages which have already been installed.
Home-page: https://colcon.readthedocs.io
Author: Scott K Logan
Author-email: logans@cottsay.net
Maintainer: Scott K Logan
Maintainer-email: logans@cottsay.net
License: Apache License, Version 2.0
Project-URL: Changelog, https://github.com/colcon/colcon-installed-package-information/milestones?direction=desc&sort=due_date&state=closed
Project-URL: GitHub, https://github.com/colcon/colcon-installed-package-information/
Keywords: colcon
Platform: UNKNOWN
Classifier: Development Status :: 3 - Alpha
Classifier: Environment :: Plugins
Classifier: Intended Audience :: Developers
Classifier: License :: OSI Approved :: Apache Software License
Classifier: Operating System :: MacOS
Classifier: Operating System :: POSIX
Classifier: Programming Language :: Python
Classifier: Topic :: Software Development :: Build Tools
Requires-Python: >=3.6
License-File: LICENSE
Requires-Dist: colcon-core
Requires-Dist: importlib-metadata ; python_version < "3.8"
Provides-Extra: test
Requires-Dist: flake8 (>=3.6.0) ; extra == 'test'
Requires-Dist: flake8-blind-except ; extra == 'test'
Requires-Dist: flake8-builtins ; extra == 'test'
Requires-Dist: flake8-class-newline ; extra == 'test'
Requires-Dist: flake8-comprehensions ; extra == 'test'
Requires-Dist: flake8-deprecated ; extra == 'test'
Requires-Dist: flake8-docstrings ; extra == 'test'
Requires-Dist: flake8-import-order ; extra == 'test'
Requires-Dist: flake8-quotes ; extra == 'test'
Requires-Dist: pep8-naming ; extra == 'test'
Requires-Dist: pylint ; extra == 'test'
Requires-Dist: pytest ; extra == 'test'
Requires-Dist: pytest-cov ; extra == 'test'
Requires-Dist: scspell3k (>=2.2) ; extra == 'test'
